sciml/__init__.py
sciml/ccc.py
sciml/metrics.py
sciml/models.py
sciml/pipelines.py
sciml/regress2.py
sciml-0.0.12.dist-info/LICENSE
sciml-0.0.12.dist-info/METADATA
sciml-0.0.12.dist-info/WHEEL
sciml-0.0.12.dist-info/top_level.txt
sciml-0.0.12.dist-info/RECORD
