Metadata-Version: 2.1
Name: sciml
Version: 0.0.12
Summary: Machine/deep learning models and toolboxes for geosciences.
Home-page: https://github.com/soonyenju/sciml
Author: Songyan Zhu
Author-email: zhusy93@gmail.com
License: MIT Licence
Keywords: Geospatial scientific ML
Platform: any
License-File: LICENSE
